[
  {
    "name": "FOHE + Magic Edtech at SXSW EDU",
    "time": "LIVE6:00 PM",
    "url": "https://lu.ma/h02mscf8",
    "location": "The Stay Put",
    "thumbnailUrl": "eb02d660-f85c-4be6-ad45-24759537e911.png",
    "index": 1
  },
  {
    "name": "Building the Future: Charter Cities, Network States & More @ Ârc Austin, with Patri Friedman & More",
    "time": "1:00 PM",
    "url": "https://lu.ma/hdue6sat",
    "location": "Capital Factory",
    "thumbnailUrl": "9bc26ecb-b9d1-4471-8f6c-df715b8f10a3.png",
    "index": 2
  },
  {
    "name": "Entrepreneur Game and Social Hour - Hang out, Connect, & Play SideHustle: the Party Game for Entrepreneurs",
    "time": "6:00 PM",
    "url": "https://lu.ma/w59ef8hj",
    "location": "Hi Sign Brewing",
    "thumbnailUrl": "b06fc232-5810-487f-8ace-4da296f68e5c.jpg",
    "index": 3
  },
  {
    "name": "Wilbe: Unscripted | Austin, TX",
    "time": "6:00 PM",
    "url": "https://lu.ma/6qsch3wh",
    "location": "Austin, Texas",
    "thumbnailUrl": "07fbed2d-2d76-4513-8009-86a3ac881acc.png",
    "index": 4
  },
  {
    "name": "OpenCoffee Club Austin - Special Edition SXSW  2025",
    "time": "8:30 AM",
    "url": "https://lu.ma/sx25opencoffee",
    "location": "Austin, Texas",
    "thumbnailUrl": "4e1bea1a-b513-460a-86d5-0d07c0cae6da.jpg",
    "index": 5
  },
  {
    "name": "FINN Partners X humble ventures: Future of Education Day",
    "time": "9:00 AM",
    "url": "https://lu.ma/2b5rkxxv",
    "location": "Atelier 1205",
    "thumbnailUrl": "b2ac3b2f-aad1-4a1a-82bb-b04b4c6486c6.jpg",
    "index": 6
  },
  {
    "name": "RP1 Open House Series: #3 (SXSW)",
    "time": "11:00 AM",
    "url": "https://lu.ma/9ahx5xkf",
    "location": "Virtual",
    "thumbnailUrl": "0ed7eb1b-b052-404f-ba39-43859c616787.png",
    "index": 7
  },
  {
    "name": "Dream Wealth Camp SXSW Edition",
    "time": "1:00 PM",
    "url": "https://lu.ma/yyytc807",
    "location": "Austin, Texas",
    "thumbnailUrl": "94e29bf0-c936-4321-91ac-d5082d8c3449.png",
    "index": 8
  },
  {
    "name": "TXHQ: Israel Downtown Rooftop Event (Save-the-Date)",
    "time": "1:00 PM",
    "url": "https://lu.ma/fibeml3u",
    "location": "Register to See Location",
    "thumbnailUrl": "4dfa4f3c-4c40-4fa7-826b-00b77aee501e.png",
    "index": 9
  },
  {
    "name": "From Sydney to Austin: EdTech and Innovation",
    "time": "4:00 PM",
    "url": "https://lu.ma/7j963krq",
    "location": "Austin, Texas",
    "thumbnailUrl": "photo-1551352912-484163ad5be9",
    "index": 10
  },
  {
    "name": "Padel & Pitch in Padel Haus.",
    "time": "4:00 PM · 5:00 PM EST",
    "url": "https://lu.ma/9j7ua48k",
    "location": "Padel Haus Williamsburg",
    "thumbnailUrl": "ecb8574a-d1dd-446e-b550-7b1c32291971.png",
    "index": 11
  },
  {
    "name": "SxSW Happy Hour Kickoff - by Rho, Navan & A/F Fund",
    "time": "7:00 PM",
    "url": "https://lu.ma/xw9r3dxa",
    "location": "Whisler's",
    "thumbnailUrl": "677dcded-9035-4c99-b1af-42532d24db88.jpg",
    "index": 12
  },
  {
    "name": "Private Founder Michelin Star Dinner (Pre-SXSW)",
    "time": "7:00 PM",
    "url": "https://lu.ma/ymh7z01q",
    "location": "Austin, Texas",
    "thumbnailUrl": "3bfe658e-2e00-40a2-adf8-dd8c9f938e7b.png",
    "index": 13
  },
  {
    "name": "SXSW: Service Design at the City of Austin",
    "time": "7:00 PM",
    "url": "https://lu.ma/45e3x72z",
    "location": "Residences at The Triangle",
    "thumbnailUrl": "f34cc949-d2b5-47d5-aca6-4963a75680c6.png",
    "index": 14
  },
  {
    "name": "SXSW 2025 - Innovation Journey Disruptivos",
    "time": "6:00 AM",
    "url": "https://lu.ma/disruptivos-sxsw2025",
    "location": "Austin Convention Center",
    "thumbnailUrl": "4769c460-4abe-4817-be0f-b6fa56383f25",
    "index": 15
  },
  {
    "name": "SXSW: Founder & Funder Spin, Sip, Social with Mercury & Cooley",
    "time": "8:30 AM",
    "url": "https://lu.ma/1zo7m9ub",
    "location": "Equinox Austin",
    "thumbnailUrl": "624b4fec-1837-40e6-b85c-44e3ab2dc79c.jpg",
    "index": 16
  },
  {
    "name": "Equitech Texas Welcome Breakfast",
    "time": "9:00 AM",
    "url": "https://lu.ma/2ao2stl2",
    "location": "Austin, Texas",
    "thumbnailUrl": "29972be0-9da8-4879-aa30-6dad8a44b268.png",
    "index": 17
  },
  {
    "name": "Investor Welcome Breakfast at Midwest House",
    "time": "9:00 AM",
    "url": "https://lu.ma/4rzl6d9p",
    "location": "315 Lavaca St",
    "thumbnailUrl": "1fe445ec-82d5-484e-89f0-ccb454ccb6a5.png",
    "index": 18
  },
  {
    "name": "FINN Partners x humble ventures: Future of Health Day Brought to you by Doceree",
    "time": "9:30 AM",
    "url": "https://lu.ma/o3r89474",
    "location": "Atelier 1205",
    "thumbnailUrl": "dff26be8-e646-4009-94e2-83d5e8ee0f53.png",
    "index": 19
  },
  {
    "name": "March - PEF Austin Breakfast - SXSW - (1st Fridays)",
    "time": "9:30 AM",
    "url": "https://lu.ma/1lkl8nzx",
    "location": "1814 E Martin Luther King Jr Blvd",
    "thumbnailUrl": "e5940da7-2c82-403f-8f5b-14a3b14e6870",
    "index": 20
  },
  {
    "name": "Midwest House 2025 - Get On The List",
    "time": "10:00 AM",
    "url": "https://lu.ma/qpgbuopz",
    "location": "315 Lavaca St",
    "thumbnailUrl": "e8e3a171-6ff1-4b3b-a29e-c58ad22262d9.png",
    "index": 21
  },
  {
    "name": "La Casa Argentina - ATCC TECH",
    "time": "10:00 AM",
    "url": "https://lu.ma/k0xqrcpk",
    "location": "Buenos Aires Café",
    "thumbnailUrl": "304fdc8c-3281-4588-ba58-b7ffb842f667.png",
    "index": 22
  },
  {
    "name": "Startup Casa 2025",
    "time": "10:00 AM",
    "url": "https://lu.ma/3secv5lz",
    "location": "Austin, Texas",
    "thumbnailUrl": "8c110989-aaab-4953-9cbd-135804f10a78.png",
    "index": 23
  },
  {
    "name": "Startup/Investor Superconnector featuring Practice Pitch",
    "time": "11:00 AM",
    "url": "https://lu.ma/ys9luzr7",
    "location": "315 Lavaca St",
    "thumbnailUrl": "14434eff-5eed-4ed3-99c8-041f7f62ae54.png",
    "index": 24
  },
  {
    "name": "SaaS Founders Mixer with Silverton Partners and Forum Ventures (Sponsored by Deel, Carta, and Zendesk)",
    "time": "11:30 AM",
    "url": "https://lu.ma/f3dfcjkb",
    "location": "Austin, Texas",
    "thumbnailUrl": "80212c61-ece6-417e-b3bd-e28b45a9837e.png",
    "index": 25
  },
  {
    "name": "TXHQ: Canada Downtown Rooftop Event (Save-the-Date)",
    "time": "1:00 PM",
    "url": "https://lu.ma/g4wlknxb",
    "location": "Register to See Location",
    "thumbnailUrl": "4dfa4f3c-4c40-4fa7-826b-00b77aee501e.png",
    "index": 26
  },
  {
    "name": "Founders N' Funders: SXSW VC Reverse Pitch",
    "time": "4:00 PM",
    "url": "https://lu.ma/ais9dokd",
    "location": "Austin, Texas",
    "thumbnailUrl": "ab889257-0fb7-4790-8f8e-6707ef95a8c1.png",
    "index": 27
  },
  {
    "name": "✨ ayana x Cherub 2025 Founders Panel 🚀",
    "time": "4:00 PM",
    "url": "https://lu.ma/vg4vkwjp",
    "location": "1114 E Cesar Chavez St",
    "thumbnailUrl": "1ae2bfec-7d7b-4585-abc3-07f7703be073.png",
    "index": 28
  },
  {
    "name": "Midwest House 2025 - Friends & Family Guest List",
    "time": "4:30 PM",
    "url": "https://lu.ma/pe7hnw07",
    "location": "315 Lavaca St",
    "thumbnailUrl": "72b6a877-84c9-4f68-b9b2-7211f5bb6ef9.png",
    "index": 29
  },
  {
    "name": "Austin: SXSW HealthTech Networking Happy Hour 🚀🍹",
    "time": "5:00 PM",
    "url": "https://lu.ma/qigwwg2u",
    "location": "Moonshine Grill",
    "thumbnailUrl": "94d0c2e0-a16f-4d11-a5f2-c113aed7f41e.jpg",
    "index": 30
  },
  {
    "name": "SXSW Fantasy Sports Engagement Summit",
    "time": "5:00 PM",
    "url": "https://lu.ma/hqv4hhg4",
    "location": "Austin, Texas",
    "thumbnailUrl": "2fb33262-bf96-4299-84e8-984c7b85bbff.png",
    "index": 31
  },
  {
    "name": "Liberty Ventures Reception at SXSW",
    "time": "5:30 PM",
    "url": "https://lu.ma/niuy89eu",
    "location": "The University of Austin",
    "thumbnailUrl": "ab7da9de-6432-48a7-aa2f-0b06d21f1b3e.png",
    "index": 32
  },
  {
    "name": "Austin Meetup - SXSW",
    "time": "5:30 PM",
    "url": "https://lu.ma/or4umeju",
    "location": "SXSW Center",
    "thumbnailUrl": "456366cf-6cb0-46db-8baf-5630771dbb6f",
    "index": 33
  },
  {
    "name": "Reverse VC Party At SXSW",
    "time": "6:00 PM",
    "url": "https://lu.ma/drde5f04",
    "location": "Hotel ZaZa Austin Downtown",
    "thumbnailUrl": "14e9052a-40a4-4b4d-916b-db6bbfd5c098.jpg",
    "index": 34
  },
  {
    "name": "#OPENSHABBAT @ SXSW 2025",
    "time": "7:30 PM",
    "url": "https://lu.ma/oltfhptd",
    "location": "Austin, Texas",
    "thumbnailUrl": "51ff7e89-dec0-44fd-8b5c-ddaaf6361b71.png",
    "index": 35
  },
  {
    "name": "SxSW Startup Crawl Happy Hour: Hosted by Tax Hack & Relay",
    "time": "8:00 PM",
    "url": "https://lu.ma/y8ng0m58",
    "location": "Austin, Texas",
    "thumbnailUrl": "dd6c0154-e56e-4c2b-bec6-fa7e9b2ebeb6.png",
    "index": 36
  },
  {
    "name": "Founder TechWalk SXSW Edition | Austin 3/8 | Sponsored by Rho",
    "time": "9:00 AM",
    "url": "https://lu.ma/7osufyy5",
    "location": "Austin",
    "thumbnailUrl": "9e0a388e-52f6-47a7-9549-668da066949c.png",
    "index": 37
  },
  {
    "name": "Hiring for Startups in the Era of Generative AI",
    "time": "9:00 AM",
    "url": "https://lu.ma/8en0ov6c",
    "location": "Austin, Texas",
    "thumbnailUrl": "fb830ce2-7f91-4ab3-afe5-c95196e154f4.png",
    "index": 38
  },
  {
    "name": "Q-Branch: Global Security and Innovation Exchange (GSIX)",
    "time": "9:00 AM",
    "url": "https://lu.ma/1bi9tn5f",
    "location": "Q-Branch Global Collaboration Center",
    "thumbnailUrl": "b4e3ed75-6515-497a-b690-aff6c9eeef00.png",
    "index": 39
  },
  {
    "name": "The Health Hustlers - Business & Networking for Health Entrepreneurs & Business Owners (SXSW Event - Badge Required)",
    "time": "10:00 AM",
    "url": "https://lu.ma/xwft78a7",
    "location": "JW Marriott Austin",
    "thumbnailUrl": "9aeea6a0-4574-4c21-a964-fa8638b6a4d1",
    "index": 40
  },
  {
    "name": "Unofficial SXSW: Viva Benefits “Morning After” Recovery Room + Pickleball Pre-Game",
    "time": "10:00 AM",
    "url": "https://lu.ma/viva-sxsw-2025",
    "location": "Mirador ATX Condos | 78704 Austin Condominiums",
    "thumbnailUrl": "c4857687-481f-488b-8899-05ad816171f7.png",
    "index": 41
  },
  {
    "name": "Coffee with Creators in Austin",
    "time": "10:00 AM",
    "url": "https://lu.ma/2c207i0w",
    "location": "Austin, Texas",
    "thumbnailUrl": "efedc488-ca5f-4f54-a187-9de3917e36a8.jpg",
    "index": 42
  },
  {
    "name": "Meetup @ SXSW: AI + Medicine",
    "time": "11:00 AM",
    "url": "https://lu.ma/v5b06ilk",
    "location": "Four Seasons Hotel Austin",
    "thumbnailUrl": "photo-1571772996211-2f02c9727629",
    "index": 43
  },
  {
    "name": "Espacio Latino 2025",
    "time": "11:30 AM",
    "url": "https://lu.ma/b58ub60b",
    "location": "Q-Branch Global Collaboration Center",
    "thumbnailUrl": "49859831-4c55-478e-8131-75eecb5cc056",
    "index": 44
  },
  {
    "name": "The Creators Playground: Brought to you by Kajabi",
    "time": "12:00 PM",
    "url": "https://lu.ma/vrclaquw",
    "location": "Austin, Texas",
    "thumbnailUrl": "24b8bb15-8866-47ef-b50d-ffcf9a66f77e.png",
    "index": 45
  },
  {
    "name": "Unofficial SXSW: PropTech Brunch + Epic Pickleball Tournament",
    "time": "12:00 PM",
    "url": "https://lu.ma/proptech-brunch-sxsw-2025",
    "location": "Mirador ATX Condos | 78704 Austin Condominiums",
    "thumbnailUrl": "165d3a4e-d316-420c-85b2-60a84879c9a5.jpg",
    "index": 46
  },
  {
    "name": "The Deal Saloon",
    "time": "12:30 PM",
    "url": "https://lu.ma/a3nm3yzh",
    "location": "Inn Cahoots",
    "thumbnailUrl": "0be99184-38b9-4e52-8dbd-7ddeecbbe862.png",
    "index": 47
  },
  {
    "name": "Impact Investment Lunch SXSW (Austin, TX)",
    "time": "12:30 PM",
    "url": "https://lu.ma/1ovntzqb",
    "location": "Austin, Texas",
    "thumbnailUrl": "3703faf6-5623-44e3-8dc1-5b8cf5fe610f.jpg",
    "index": 48
  },
  {
    "name": "TXHQ: Mexico Downtown Rooftop Event (Save-the-Date)",
    "time": "1:00 PM",
    "url": "https://lu.ma/bmy0okk2",
    "location": "Register to See Location",
    "thumbnailUrl": "4dfa4f3c-4c40-4fa7-826b-00b77aee501e.png",
    "index": 49
  },
  {
    "name": "DivInc IWD Pop-Up 2025",
    "time": "1:00 PM",
    "url": "https://lu.ma/divincsx25",
    "location": "506 Congress Ave.",
    "thumbnailUrl": "cd232e5d-224b-4fe2-a2c3-ff808d6fd839.png",
    "index": 50
  },
  {
    "name": "✨💛 Austin IWD Trail Walk & Social | March",
    "time": "1:30 PM",
    "url": "https://lu.ma/hrcyi613",
    "location": "Austin, Texas",
    "thumbnailUrl": "779c22cf-cb2b-485a-9852-b2b3f63d22a8",
    "index": 51
  },
  {
    "name": "BBQ, Brunch & Brands by GetResponse and TikTok LIVE Creator Networks",
    "time": "2:00 PM",
    "url": "https://lu.ma/hj83cnla",
    "location": "Austin",
    "thumbnailUrl": "cd496cdb-eb4d-415f-9da0-7113255a6adb.png",
    "index": 52
  },
  {
    "name": "B2B Marketing Austin Experience: Unique Networking-Tour",
    "time": "3:30 PM",
    "url": "https://lu.ma/by6z654a",
    "location": "Austin, Texas",
    "thumbnailUrl": "f38ee2ab-1640-4330-a626-b9e5212673eb.png",
    "index": 53
  },
  {
    "name": "CULTURE3 @ SXSW: Brands & Impact In A Changing World",
    "time": "4:00 PM",
    "url": "https://lu.ma/630o7pcv",
    "location": "Palm Door On Sixth",
    "thumbnailUrl": "e80c6a80-a343-4368-b2ff-d5f78eccecd0.png",
    "index": 54
  },
  {
    "name": "Film, Tech, & AI Converge",
    "time": "4:00 PM",
    "url": "https://lu.ma/ua28glgz",
    "location": "Austin, Texas",
    "thumbnailUrl": "332d68ab-363d-4e11-945a-cfd401454ee4.png",
    "index": 55
  },
  {
    "name": "The Founder's Deal (Poker) @ Lumos House",
    "time": "4:00 PM",
    "url": "https://lu.ma/foundersdeal",
    "location": "Austin, Texas",
    "thumbnailUrl": "0658b3b9-8e5d-4ce4-a5da-5f652948b6ed.png",
    "index": 56
  },
  {
    "name": "Bold Prompts: Meet Germany’s Top AI Startups",
    "time": "4:30 PM",
    "url": "https://lu.ma/0xkjqxo0",
    "location": "Speakeasy",
    "thumbnailUrl": "6651bf4e-992b-4299-8795-fed972507d66.png",
    "index": 57
  },
  {
    "name": "Make a Splash: Filmmaker x Industry Mixer",
    "time": "5:00 PM",
    "url": "https://lu.ma/240smrod",
    "location": "The Aquarium on 6th",
    "thumbnailUrl": "8e2ef608-3e8d-4316-926f-d6ab8fa2faf7.png",
    "index": 58
  },
  {
    "name": "🎉 LaFamilia @ SXSW '25 (unofficial)",
    "time": "6:00 PM",
    "url": "https://lu.ma/bx8m8e3r",
    "location": "Austin, Texas",
    "thumbnailUrl": "39dec8ee-5eb5-435f-9f73-817fe98cd90c.png",
    "index": 59
  },
  {
    "name": "Lumos House Opening Night",
    "time": "8:00 PM",
    "url": "https://lu.ma/wafjr38p",
    "location": "Austin, Texas",
    "thumbnailUrl": "4de90184-b975-4185-9547-e2bdbe23ceb2.png",
    "index": 60
  },
  {
    "name": "Work For Higher Austin",
    "time": "9:00 PM",
    "url": "https://lu.ma/9kutc8t2",
    "location": "Summit Rooftop",
    "thumbnailUrl": "70ba7a46-054c-408b-8c58-78db7ea18b9e.png",
    "index": 61
  },
  {
    "name": "Sunday Morning Networking Run - For Founders & Marketers",
    "time": "8:00 AM",
    "url": "https://lu.ma/xpa40y0s",
    "location": "1413 1/2 W 38th St",
    "thumbnailUrl": "4d2dbfb3-0a25-4738-82e8-b048e82e6245.jpg",
    "index": 62
  },
  {
    "name": "The Prelude at Lumos House",
    "time": "8:30 AM",
    "url": "https://lu.ma/9x378mnw",
    "location": "Austin, Texas",
    "thumbnailUrl": "79c5707b-d20d-4c64-bd34-9919942a011d.png",
    "index": 63
  },
  {
    "name": "Accelerating Innovation Across the Open Social Web — AM",
    "time": "9:00 AM",
    "url": "https://lu.ma/oc052rvr",
    "location": "412 Congress Ave.",
    "thumbnailUrl": "1f4a9c0d-a167-4ccc-8254-9f8f5fbc4ed5.jpg",
    "index": 64
  },
  {
    "name": "Casa TechMex 2025",
    "time": "9:00 AM",
    "url": "https://lu.ma/hnyq5mi2",
    "location": "Capital Factory",
    "thumbnailUrl": "1d43b597-7d36-4497-89a9-ffe5b05420db.png",
    "index": 65
  },
  {
    "name": "Fediverse House (All Events)",
    "time": "9:00 AM",
    "url": "https://lu.ma/xbve5fa0",
    "location": "412 Congress Ave.",
    "thumbnailUrl": "d79bff91-6e4a-493a-98d8-a273107ea153.jpg",
    "index": 66
  },
  {
    "name": "Going BIG in TEXAS - Slovak House",
    "time": "9:30 AM",
    "url": "https://lu.ma/hc5gepdn",
    "location": "Q-Branch Global Collaboration Center",
    "thumbnailUrl": "8e4f51b1-f4f7-4312-8ad2-4d2c9b973837.png",
    "index": 67
  },
  {
    "name": "Breaking the 18-Month CMO Curse: Redefining the Future of Marketing Leadership",
    "time": "9:30 AM",
    "url": "https://lu.ma/cxj7jcw9",
    "location": "800 Brazos St ste 300",
    "thumbnailUrl": "16613cd9-9770-402e-a318-81b6a3fe6bc7.png",
    "index": 68
  },
  {
    "name": "SXSW Early-Stage B2B SaaS Founders & Funders Breakfast Club",
    "time": "9:30 AM",
    "url": "https://lu.ma/wizj0q6i",
    "location": "Austin, Texas",
    "thumbnailUrl": "4fcfef3d-f2b7-4321-b4de-742ac2e5c4d3.png",
    "index": 69
  },
  {
    "name": "AI House @ SXSW - Day 1",
    "time": "10:00 AM",
    "url": "https://lu.ma/sxsw-ai-house-day1",
    "location": "1705 Guadalupe St ste 300",
    "thumbnailUrl": "acc99fea-e0af-4aa3-8fd1-61db7717795a.png",
    "index": 70
  },
  {
    "name": "Builders’ Brunch: Connecting Innovators & Investors",
    "time": "10:30 AM",
    "url": "https://lu.ma/3ymnhsfe",
    "location": "Austin, Texas",
    "thumbnailUrl": "photo-1520950237264-dfe336995c34",
    "index": 71
  },
  {
    "name": "Brews & Bots @ SXSW '25 (unofficial)",
    "time": "11:00 AM",
    "url": "https://lu.ma/zgkfs16z",
    "location": "3901 Woodbury Dr",
    "thumbnailUrl": "74e2031d-f57c-4bd6-a4e7-88fa179d8e73.jpg",
    "index": 72
  },
  {
    "name": "Industry Journalists Tell All",
    "time": "11:15 AM",
    "url": "https://lu.ma/znnk8960",
    "location": "Palm Door On Sixth",
    "thumbnailUrl": "a1d83aba-b220-4d17-87da-8e1c964819dc.png",
    "index": 73
  },
  {
    "name": "The Attention Economy: How to Entertain in 2025",
    "time": "12:30 PM",
    "url": "https://lu.ma/9jyfkooe",
    "location": "Palm Door On Sixth",
    "thumbnailUrl": "c81f2fb5-9896-4892-8627-9067abda9a8f.png",
    "index": 74
  },
  {
    "name": "TXHQ: Ireland Downtown Rooftop Event (Save-the-Date)",
    "time": "1:00 PM",
    "url": "https://lu.ma/nujtuemc",
    "location": "Register to See Location",
    "thumbnailUrl": "4dfa4f3c-4c40-4fa7-826b-00b77aee501e.png",
    "index": 75
  },
  {
    "name": "Culture House ATX @ SXSW - VIP Guest",
    "time": "1:00 PM",
    "url": "https://lu.ma/4pykutnt",
    "location": "Austin, Texas",
    "thumbnailUrl": "df148c37-1e00-4f91-a8c9-fb0b702a6aae.png",
    "index": 76
  },
  {
    "name": "Tech Founders and Investors at Padel39",
    "time": "1:00 PM",
    "url": "https://lu.ma/50eaq1xm",
    "location": "Austin, Texas",
    "thumbnailUrl": "e0ce9a1e-7819-45a7-adf9-bf7d4c327af6.jpg",
    "index": 77
  },
  {
    "name": "From Storytelling to Storyselling - The Commercial Power of Narrative",
    "time": "1:00 PM",
    "url": "https://lu.ma/crfq2k5m",
    "location": "Palm Door On Sixth",
    "thumbnailUrl": "9cc6e9a8-6541-49af-9fd5-a05b73ccc6e3.png",
    "index": 78
  },
  {
    "name": "Culture House ATX @ SXSW - All Events Tickets",
    "time": "1:00 PM",
    "url": "https://lu.ma/qcx30huq",
    "location": "Austin, Texas",
    "thumbnailUrl": "789651e8-7443-4ff6-87cd-e72850666e3a.png",
    "index": 79
  },
  {
    "name": "Culture House ATX @ SXSW - cultureSPARK Brunch",
    "time": "1:00 PM",
    "url": "https://lu.ma/xkca9795",
    "location": "Austin, Texas",
    "thumbnailUrl": "03b301bc-24c3-46e3-a4e9-c9dee07868bc.png",
    "index": 80
  },
  {
    "name": "Earth's Biggest Brief: The World's First Agency For Nature",
    "time": "1:30 PM",
    "url": "https://lu.ma/fdt561t7",
    "location": "Palm Door On Sixth",
    "thumbnailUrl": "5eb11b7c-24a7-4cd0-8e49-999652dc0936.png",
    "index": 81
  },
  {
    "name": "Developer Meetup",
    "time": "2:00 PM",
    "url": "https://lu.ma/bvump3m6",
    "location": "412 Congress Ave.",
    "thumbnailUrl": "ed1c43b7-2e55-4edc-8812-a721984fcd70.jpg",
    "index": 82
  },
  {
    "name": "East Meets West: CREATORPALOOZA 2025 in ATX",
    "time": "2:00 PM",
    "url": "https://lu.ma/lgyj84vt",
    "location": "Austin, Texas",
    "thumbnailUrl": "419ea327-37ae-40f6-84f0-8da74ad8f7b0.png",
    "index": 83
  },
  {
    "name": "From Touchdowns to Goals: Texas, the World Cup, and the Future of Football",
    "time": "3:00 PM",
    "url": "https://lu.ma/v9p5mhfs",
    "location": "Palm Door On Sixth",
    "thumbnailUrl": "8415bf73-8882-49a1-bf6d-aca2fc504cce.png",
    "index": 84
  },
  {
    "name": "Accelerating Innovation Across the Open Social Web — PM",
    "time": "4:00 PM",
    "url": "https://lu.ma/cnr8fi3j",
    "location": "412 Congress Ave.",
    "thumbnailUrl": "ae255204-dc0d-4f9a-bda1-1d67dead6ec4.jpg",
    "index": 85
  },
  {
    "name": "London Calling - A New York Times Must Visit Hub in 2025 Fueled by Creativity & Innovation",
    "time": "4:00 PM",
    "url": "https://lu.ma/ud8fs3l0",
    "location": "Austin, Texas",
    "thumbnailUrl": "fad77d34-2568-4948-b17a-6029de77b78d.png",
    "index": 86
  },
  {
    "name": "Culture House ATX @ SXSW - Day Party",
    "time": "4:00 PM",
    "url": "https://lu.ma/nx5yrnnf",
    "location": "Austin, Texas",
    "thumbnailUrl": "321c73a9-8d16-449d-ba50-8665e0c66cfb.png",
    "index": 87
  },
  {
    "name": "The Future of Hardware, Software & IoT (Happy Hour at SXSW)",
    "time": "5:00 PM",
    "url": "https://lu.ma/o6lgwwww",
    "location": "Austin, Texas",
    "thumbnailUrl": "00a47420-33a1-415e-a818-fbe4527e05f0.jpg",
    "index": 88
  },
  {
    "name": "Asian Founders & Creators by Austin Creator House",
    "time": "5:30 PM",
    "url": "https://lu.ma/epcepza5",
    "location": "Austin, Texas",
    "thumbnailUrl": "9c1977f3-65e8-4090-878a-e2131a26ca73.png",
    "index": 89
  },
  {
    "name": "Lumos House VIP Founder Dinner",
    "time": "6:00 PM",
    "url": "https://lu.ma/083ysswy",
    "location": "Austin, Texas",
    "thumbnailUrl": "f25b4020-db89-4286-9207-ba24f774f09a.png",
    "index": 90
  },
  {
    "name": "[SXSW] Not-Your-Regular-Meetup : Build Your Village",
    "time": "6:00 PM",
    "url": "https://lu.ma/d1amvwqm",
    "location": "Austin, Texas",
    "thumbnailUrl": "c7609b2c-24f2-4132-9560-6aba44af8114.png",
    "index": 91
  },
  {
    "name": "Ending Hunger Today, Tomorrow, and Forever with Kellanova & Albertsons",
    "time": "6:00 PM",
    "url": "https://lu.ma/08l5vxro",
    "location": "Austin, Texas",
    "thumbnailUrl": "83e9d673-3287-4266-b6eb-0e2b7dd80c3c",
    "index": 92
  },
  {
    "name": "The Open Social Social",
    "time": "7:00 PM",
    "url": "https://lu.ma/vqb0crrl",
    "location": "412 Congress Ave.",
    "thumbnailUrl": "f1379193-fb12-473d-a4ce-21cfadb3a191.jpg",
    "index": 93
  },
  {
    "name": "Austin Marketers Dinner Presented by Popular Pays",
    "time": "7:30 PM · 6:30 PM CST",
    "url": "https://lu.ma/k3s7gsm9",
    "location": "Austin, Texas",
    "thumbnailUrl": "9af21635-b0fa-4b59-a0c9-07b7c23c23ed.png",
    "index": 94
  },
  {
    "name": "Connecting the Americas | During SXSW | Special Brazil Edition",
    "time": "8:00 AM",
    "url": "https://lu.ma/kvsjs584",
    "location": "Fogo De Chao - Austin",
    "thumbnailUrl": "88d1cb6b-c27d-4d95-a498-b7492a7efa18.jpg",
    "index": 95
  },
  {
    "name": "2nd Annual SX Pitch and Run!🤠",
    "time": "9:00 AM",
    "url": "https://lu.ma/8jsxct16",
    "location": "The Loop Running Supply",
    "thumbnailUrl": "4ec4e9c5-fd7c-436b-9a18-8c4594fafe6d.png",
    "index": 96
  },
  {
    "name": "SXSW Low-Code Builders Meetup (with Zapier & Ops Department)",
    "time": "9:00 AM",
    "url": "https://lu.ma/em99fz1d",
    "location": "Cosmic Pickle",
    "thumbnailUrl": "d24c9b9d-4517-42d7-8445-7b8dfec0c0cb.png",
    "index": 97
  },
  {
    "name": "The New Playbook",
    "time": "9:00 AM",
    "url": "https://lu.ma/dvfp9lri",
    "location": "412 Congress Ave.",
    "thumbnailUrl": "e85968cd-bfec-4bba-923f-708c67f02533.jpg",
    "index": 98
  },
  {
    "name": "The Future of Hardware, Software & IoT (Executive Breakfast, SXSW)",
    "time": "9:00 AM",
    "url": "https://lu.ma/i0hulfu4",
    "location": "110 E 2nd St",
    "thumbnailUrl": "64e5bbc1-bf47-469d-9121-678eab2ccf98.jpg",
    "index": 99
  },
  {
    "name": "TEXAS EMBASSY: Health & Human Performance",
    "time": "9:00 AM",
    "url": "https://lu.ma/cu7cbvmk",
    "location": "Q-Branch Global Collaboration Center",
    "thumbnailUrl": "8ff09ab9-0740-4a71-a091-dc9ab6fd3d26.png",
    "index": 100
  },
  {
    "name": "AI x Journalism House 2025",
    "time": "9:30 AM",
    "url": "https://lu.ma/aj74ayou",
    "location": "Austin, Texas",
    "thumbnailUrl": "0b2dd223-42a1-41af-821a-0444b76d4c19",
    "index": 101
  },
  {
    "name": "AI House @ SXSW - Day 2",
    "time": "10:00 AM",
    "url": "https://lu.ma/sxsw-ai-house-day2",
    "location": "1705 Guadalupe St ste 300",
    "thumbnailUrl": "3ba846d0-0057-4cd7-bb2e-70524be37a77.png",
    "index": 102
  },
  {
    "name": "Marketing Leaders Brunch",
    "time": "11:00 AM",
    "url": "https://lu.ma/r7ljhgg8",
    "location": "Austin, Texas",
    "thumbnailUrl": "411ffbfb-1250-4e94-8522-554405fa1758.png",
    "index": 103
  },
  {
    "name": "Frontiers of Innovation Day in Austin TX (SXSW 2025) | Presented by the Frontier Collective",
    "time": "12:30 PM · 10:30 AM PDT",
    "url": "https://lu.ma/v4a9d6ix",
    "location": "Fairmont Austin",
    "thumbnailUrl": "6400038e-4031-4b77-a741-02c2de49fa7a.png",
    "index": 104
  },
  {
    "name": "TXHQ: Australia Downtown Rooftop Event (Save-the-Date)",
    "time": "1:00 PM",
    "url": "https://lu.ma/xfzg480b",
    "location": "Register to See Location",
    "thumbnailUrl": "4dfa4f3c-4c40-4fa7-826b-00b77aee501e.png",
    "index": 105
  },
  {
    "name": "Publishers and Journalists in the Fediverse",
    "time": "3:00 PM",
    "url": "https://lu.ma/k5meba69",
    "location": "412 Congress Ave.",
    "thumbnailUrl": "54b7c609-7e1e-42a6-83fe-aa3591ab1d33.jpg",
    "index": 106
  },
  {
    "name": "Crowdstake @ SXSW 2025",
    "time": "5:00 PM",
    "url": "https://lu.ma/qgwzs5ha",
    "location": "Mort Subite Belgian Beer Bar",
    "thumbnailUrl": "88a0bd24-8f12-4596-a7b0-26e1929bc01f.png",
    "index": 107
  },
  {
    "name": "LTX Studio: Austin Workshop & Mixer at Hotel Magdalena",
    "time": "5:00 PM · 4:00 PM CST",
    "url": "https://lu.ma/aes90j4y",
    "location": "Austin, Texas",
    "thumbnailUrl": "5bf672ed-c18c-4dd0-9be3-7ae70c1c8017.png",
    "index": 108
  },
  {
    "name": "SXSW XR Mixer: VR, AR, XR Meetup",
    "time": "5:00 PM · 3:00 PM PDT",
    "url": "https://lu.ma/8ofb2d9x",
    "location": "Austin, Texas",
    "thumbnailUrl": "cf44299a-b476-4552-b145-7ee92e9e6c39.gif",
    "index": 109
  },
  {
    "name": "404 Takeover and Party",
    "time": "5:00 PM",
    "url": "https://lu.ma/hffhi9sn",
    "location": "412 Congress Ave.",
    "thumbnailUrl": "dea5291b-7ae5-40dd-a6bb-64305cc48819.jpg",
    "index": 110
  },
  {
    "name": "The Untold Story of Spin with Euwyn Poon (Founder, Spin)",
    "time": "6:30 PM",
    "url": "https://lu.ma/48yb2cpe",
    "location": "Austin, Texas",
    "thumbnailUrl": "aace6ece-bc4f-4168-8cf0-8a9945100b44.png",
    "index": 111
  },
  {
    "name": "GP&LP FAMILY OFFICES 🌟 MICHELIN STAR 🌟 DINNER & SXSW KICKOFF",
    "time": "8:00 PM",
    "url": "https://lu.ma/r8iomy94",
    "location": "Austin, Texas",
    "thumbnailUrl": "a74ad4ee-d14c-49d1-96ef-a0e60de27d1e",
    "index": 112
  },
  {
    "name": "Topgolf Tech Mixer with BairesDev",
    "time": "8:00 PM · 7:00 PM CST",
    "url": "https://lu.ma/b9njszqs",
    "location": "Austin, Texas",
    "thumbnailUrl": "73554a98-698d-409a-8df1-4c9f4b17514f.png",
    "index": 113
  },
  {
    "name": "Founders Run & Coffee! (SXSW Edition)",
    "time": "7:00 AM",
    "url": "https://lu.ma/yesro4q3",
    "location": "Austin",
    "thumbnailUrl": "8a865e29-73e3-47cb-bd44-b22f15e0fe33",
    "index": 114
  },
  {
    "name": "Responsible AI Investors - SXSW",
    "time": "8:30 AM",
    "url": "https://lu.ma/PolygrafAI",
    "location": "Austin, Texas",
    "thumbnailUrl": "835b54db-438c-4363-8287-1720bd6a5846",
    "index": 115
  },
  {
    "name": "TEXAS EMBASSY: Texas Innovation Ecosystem",
    "time": "9:00 AM",
    "url": "https://lu.ma/qa7z5etu",
    "location": "Q-Branch Global Collaboration Center",
    "thumbnailUrl": "e74a8d35-89b8-476e-88be-047881380f20.png",
    "index": 116
  },
  {
    "name": "AI for Women",
    "time": "10:00 AM",
    "url": "https://lu.ma/c23uxbvl",
    "location": "Austin",
    "thumbnailUrl": "c8eb2478-6a6c-4af3-83aa-b3937685821f.png",
    "index": 117
  },
  {
    "name": "UKHOUSE @ SXSW - The Future of AI: Who wins, who loses and how do we shape it?",
    "time": "10:00 AM",
    "url": "https://lu.ma/gi7x8i6j",
    "location": "Austin, Texas",
    "thumbnailUrl": "f353f216-af5d-4222-a580-da48cd05a71e.png",
    "index": 118
  },
  {
    "name": "Entertainment, Music, & Media Brunch",
    "time": "11:00 AM",
    "url": "https://lu.ma/bsz61k6c",
    "location": "Austin, Texas",
    "thumbnailUrl": "c23e005c-9198-470c-9bd5-293b0beeea62.png",
    "index": 119
  },
  {
    "name": "Mionetto Salone",
    "time": "12:00 PM",
    "url": "https://lu.ma/vesqrkf7",
    "location": "Mexic-Arte Museum",
    "thumbnailUrl": "5ac060d6-a92a-45cf-912d-38f19192fecc.jpg",
    "index": 120
  },
  {
    "name": "WE ARE ARISING GREEN CARPET EVENT",
    "time": "1:00 PM",
    "url": "https://lu.ma/z8tubmx9",
    "location": "Indra's Awarehouse",
    "thumbnailUrl": "6e401872-c970-4cd1-8961-20f714b9dcf3",
    "index": 121
  },
  {
    "name": "GLEAN'S SXSW AI OPEN HOUSE",
    "time": "1:00 PM",
    "url": "https://lu.ma/odm58cjd",
    "location": "Electric Shuffle Austin",
    "thumbnailUrl": "eaf3cdf4-48ae-431e-a604-216abd1c21cd.jpg",
    "index": 122
  },
  {
    "name": "Authenticity Is Currency - How to Build a Brand People Genuinely Want to Follow",
    "time": "3:30 PM",
    "url": "https://lu.ma/gug5sprq",
    "location": "Austin, Texas",
    "thumbnailUrl": "0c852baa-1926-43c9-be87-988df2760d11.png",
    "index": 123
  },
  {
    "name": "7BC Global VC Demo Day & VC Fund of Funds launch announcement & Austin Boomtown VC Insight Panel",
    "time": "4:00 PM",
    "url": "https://lu.ma/mgsso7p2",
    "location": "CBRE",
    "thumbnailUrl": "8d6e10d7-2797-4d96-92f9-0c8622059390.png",
    "index": 124
  },
  {
    "name": "SXSW Rooftop Tech Mixer",
    "time": "4:00 PM",
    "url": "https://lu.ma/ymrg3h06",
    "location": "Austin, Texas",
    "thumbnailUrl": "666965d8-4dd4-45b3-8cfa-376b6d830973.png",
    "index": 125
  },
  {
    "name": "SXSW She Means Business: Ask Her Anything Hot Seat",
    "time": "4:00 PM",
    "url": "https://lu.ma/z7vcyzns",
    "location": "Austin, Texas",
    "thumbnailUrl": "1f7aa54c-b81f-41d2-a544-709e9fb85451.png",
    "index": 126
  },
  {
    "name": "NachoTuesday: SaaS & AI Founder + Investor Happy Hour",
    "time": "5:00 PM",
    "url": "https://lu.ma/4stbro58",
    "location": "Austin, Texas",
    "thumbnailUrl": "eed91567-5e5c-4d8b-a3c6-1c9ef9ddfe4e.png",
    "index": 127
  },
  {
    "name": "Bo$$ Bites Austin (During SXSW)",
    "time": "5:00 PM",
    "url": "https://lu.ma/boss-bites-austin",
    "location": "Austin, Texas",
    "thumbnailUrl": "34c2600d-851d-41ef-9821-9d1673b765de.png",
    "index": 128
  },
  {
    "name": "Datasent VIP Lounge: Founders & Investors Cocktail Hour",
    "time": "5:00 PM",
    "url": "https://lu.ma/aho5t6f2",
    "location": "The Red Fridge Society",
    "thumbnailUrl": "2be6ed56-70f2-4afd-85e9-496d1f8d3b60.jpg",
    "index": 129
  },
  {
    "name": "The Future of Middleware: Bridging the Gap to Modernization",
    "time": "5:30 PM",
    "url": "https://lu.ma/7e2tnkz3",
    "location": "Winstead PC - Austin",
    "thumbnailUrl": "0e917fe9-7cc0-4ef4-b8d2-694e7f73d51f.png",
    "index": 130
  },
  {
    "name": "AI Night ATX ~ w/ Cloudflare, GitHub, ElevenLabs & Jam.dev",
    "time": "6:00 PM",
    "url": "https://lu.ma/ai-night-atx",
    "location": "Cloudflare",
    "thumbnailUrl": "8ba6619e-5f80-4106-b204-eb361da555dd.png",
    "index": 131
  },
  {
    "name": "Batter Up! Austin",
    "time": "6:00 PM",
    "url": "https://lu.ma/BU-ATX2025",
    "location": "Austin, Texas",
    "thumbnailUrl": "6a14a7a0-bae7-46b3-a6d7-3ad8268642af",
    "index": 132
  },
  {
    "name": "Berlin Flat — Austin Edition",
    "time": "6:00 PM",
    "url": "https://lu.ma/hnz0zs1x",
    "location": "Austin",
    "thumbnailUrl": "bff998ef-5b2a-4f1c-b612-855af6d977f5.gif",
    "index": 133
  },
  {
    "name": "Austin Digital Social Networking Mixer During SXSW",
    "time": "6:00 PM",
    "url": "https://lu.ma/fgovdv4g",
    "location": "1114 E Cesar Chavez St",
    "thumbnailUrl": "1dd24ef9-3460-400b-962d-c67fcda2dec2.webp",
    "index": 134
  },
  {
    "name": "3rd Annual Context Ventures & Scout Ventures Happy Hour",
    "time": "6:00 PM",
    "url": "https://lu.ma/sxswhappyhour2025",
    "location": "Zilker Brewing Company and Taproom",
    "thumbnailUrl": "70f80515-8ab5-41c5-9f51-25e21c103957.png",
    "index": 135
  },
  {
    "name": "Beyond Productivity: AI and the Future of Work",
    "time": "6:30 PM",
    "url": "https://lu.ma/idnehjwp",
    "location": "Austin, Texas",
    "thumbnailUrl": "e8653a61-1387-403c-9a3d-465a22090552.jpg",
    "index": 136
  },
  {
    "name": "SXSW AI & Innovation VIP Forum",
    "time": "7:00 PM · 6:00 PM CST",
    "url": "https://lu.ma/wjx2l7gn",
    "location": "1519 W 29th St",
    "thumbnailUrl": "10494a43-2d52-48c9-b4cf-c8f2046a05c8.png",
    "index": 137
  },
  {
    "name": "The Ace Exchange",
    "time": "7:00 PM",
    "url": "https://lu.ma/zgsye0oq",
    "location": "Austin, Texas",
    "thumbnailUrl": "7a1ee710-5060-4f58-8d14-8e544bd573f4.png",
    "index": 138
  },
  {
    "name": "The Cometa Supper Club: SXSW 2025 Edition",
    "time": "8:30 PM",
    "url": "https://lu.ma/n6fwcxcb",
    "location": "Austin, Texas",
    "thumbnailUrl": "8b3fcdbe-e273-460b-ae66-ddacc95431bc.png",
    "index": 139
  },
  {
    "name": "Presented by Michigan: JMSN at SXSW",
    "time": "10:00 PM",
    "url": "https://lu.ma/uq8rhicw",
    "location": "Inn Cahoots",
    "thumbnailUrl": "25b56879-3a0b-49b7-9ad9-57fae2a4ee1d.png",
    "index": 140
  },
  {
    "name": "The International House",
    "time": "10:00 AM",
    "url": "https://lu.ma/h1fbfm3a",
    "location": "Austin Central Library, Austin Public Library",
    "thumbnailUrl": "f3a4e9a9-4fd6-4c64-94e6-e2a19e5c07a0",
    "index": 141
  },
  {
    "name": "Private SXSW Launch: Authentic Texas BBQ Experience for Investors, Founders, and Product Leaders",
    "time": "12:00 PM",
    "url": "https://lu.ma/h9jf24za",
    "location": "Austin",
    "thumbnailUrl": "photo-1456049616707-070399496327",
    "index": 142
  },
  {
    "name": "International Pitch Competition @ The International House 2025",
    "time": "2:30 PM",
    "url": "https://lu.ma/ui7mowcx",
    "location": "Austin Central Library, Austin Public Library",
    "thumbnailUrl": "a1f1356a-add6-4c09-af5d-3e2dfccca8a2.png",
    "index": 143
  },
  {
    "name": "Resilient and Rising: The State and Future of Inclusion for US in Tech",
    "time": "5:00 PM",
    "url": "https://lu.ma/g346ac1j",
    "location": "Atlassian",
    "thumbnailUrl": "90d4f5c2-3925-4afe-a5ae-00c3baad6b4b.png",
    "index": 144
  },
  {
    "name": "Climate Round Up: Innovation Showcase 2025",
    "time": "5:00 PM",
    "url": "https://lu.ma/sxsw-climate-2025",
    "location": "Austin, Texas",
    "thumbnailUrl": "89a8c952-734c-4a56-830d-a96469ff7f5b.png",
    "index": 145
  },
  {
    "name": "ATX Podcast Superfans MeetUp",
    "time": "5:00 PM",
    "url": "https://lu.ma/il9wfgs0",
    "location": "Register to See Location",
    "thumbnailUrl": "ac949ff6-893f-4092-ac5a-d2eedc702400.jpg",
    "index": 146
  },
  {
    "name": "Elevate & Unwind Happy Hour",
    "time": "5:00 PM",
    "url": "https://lu.ma/2ycemwhh",
    "location": "Fogo De Chao - Austin",
    "thumbnailUrl": "6d19de4d-7dc9-43c7-a4aa-c61c4adff5a4.png",
    "index": 147
  },
  {
    "name": "Casting Call: Founder’s Feud at The International House 2025",
    "time": "5:00 PM",
    "url": "https://lu.ma/mtu9rwds",
    "location": "Austin Central Library, Austin Public Library",
    "thumbnailUrl": "cf4813bc-63c7-489b-8d16-2fbe3af60e1a.png",
    "index": 148
  },
  {
    "name": "『MELT』150+ Founders x Investors Dynamic Network for SXSW",
    "time": "6:00 PM · 4:00 PM PDT",
    "url": "https://lu.ma/7k9f332g",
    "location": "Austin, Texas",
    "thumbnailUrl": "245a5c74-bd5f-401e-a0ac-52be9b23690c.png",
    "index": 149
  },
  {
    "name": "BEYOND THE BLOCK ATX",
    "time": "6:00 PM",
    "url": "https://lu.ma/k6r6btae",
    "location": "Club 420 ATX. Nightclub and Lounge.",
    "thumbnailUrl": "6d67b32c-4970-42ab-b794-503826836efb.jpg",
    "index": 150
  },
  {
    "name": "SXSW AI HOUSE PARTY with Glean & Codeium",
    "time": "7:00 PM",
    "url": "https://lu.ma/jslqyz57",
    "location": "Electric Shuffle Austin",
    "thumbnailUrl": "a1de6466-8675-4dbb-a4d9-9959183526ac.jpg",
    "index": 151
  },
  {
    "name": "Duetti Party in Austin",
    "time": "8:00 PM",
    "url": "https://lu.ma/cxa4dgea",
    "location": "Devil May Care",
    "thumbnailUrl": "229fa0ee-dd07-4742-9cec-accf8f90c70c.png",
    "index": 152
  },
  {
    "name": "The International House After Dark",
    "time": "8:00 PM",
    "url": "https://lu.ma/8zcl2v4m",
    "location": "Austin Central Library, Austin Public Library",
    "thumbnailUrl": "25b0bbdd-2874-41b1-bb6b-af20caba373c.png",
    "index": 153
  },
  {
    "name": "8th Annual SXSW LATINAPALOOZA   featuring Patricia Vonne  No Badges Required          21+ FREE DAY SHOW!!!",
    "time": "12:00 PM",
    "url": "https://lu.ma/t9rbx7pc",
    "location": "The Continental Club",
    "thumbnailUrl": "83c58b61-5e60-4d29-ae53-0a945ae3f7e1.png",
    "index": 154
  },
  {
    "name": "Amplitude x Braze Austin Meetup - SXSW",
    "time": "12:00 PM",
    "url": "https://lu.ma/szh598np",
    "location": "RichesArt Events",
    "thumbnailUrl": "247532fb-2a79-4de4-91b1-752855f5b1b8",
    "index": 155
  },
  {
    "name": "SXSW Austin Crypto Social",
    "time": "4:00 PM",
    "url": "https://lu.ma/4jw21677",
    "location": "To Be Announced",
    "thumbnailUrl": "7abd5e90-3281-41d2-a23a-0e17ddb00c0e.png",
    "index": 156
  },
  {
    "name": "Austin DeoVR Networking Meet-Up",
    "time": "5:00 PM",
    "url": "https://lu.ma/pezruicj",
    "location": "Austin",
    "thumbnailUrl": "f593f919-474c-4752-8e0c-0b4076170d37",
    "index": 157
  },
  {
    "name": "Austin Eclipse Festival- Portal To A New World",
    "time": "6:00 PM",
    "url": "https://lu.ma/arj4ufx9",
    "location": "The Portal",
    "thumbnailUrl": "500f8353-7a7f-47d4-b63a-bfdb9353ae52.png",
    "index": 158
  },
  {
    "name": "Your Startup Sucks (SWSW) Pitch Comedy Show",
    "time": "6:30 PM",
    "url": "https://lu.ma/csaktahl",
    "location": "2201 Lake Austin Blvd",
    "thumbnailUrl": "dc1ae3be-6dee-415b-a546-705283b696ec.png",
    "index": 159
  },
  {
    "name": "Investors & Startups Reception x SXSW 2025",
    "time": "6:30 PM",
    "url": "https://lu.ma/u9lefctx",
    "location": "Austin",
    "thumbnailUrl": "e5e40846-231a-4e69-aac7-8884e056c3c5.png",
    "index": 160
  },
  {
    "name": "Future of Fashion at SXSW: Where Fashion, Tech, and Community Intersect",
    "time": "12:00 PM",
    "url": "https://lu.ma/e0kcffcy",
    "location": "Mira Mira Venue",
    "thumbnailUrl": "c3afc178-b407-48e7-b2e7-7a7ad4f5f241.png",
    "index": 161
  },
  {
    "name": "[SXSW] - Degens - Cinema Projection 🍿",
    "time": "4:30 PM",
    "url": "https://lu.ma/2tqsxf1n",
    "location": "Violet Crown Cinema",
    "thumbnailUrl": "d5ecd19e-1e19-49d8-bea5-dc7d68a1953d.png",
    "index": 162
  },
  {
    "name": "🥣⚡🧇  Official Unofficial SatoshiO's xSW Breakfast Party",
    "time": "9:30 AM",
    "url": "https://lu.ma/486bur0j",
    "location": "Austin, Texas",
    "thumbnailUrl": "91381ec8-8767-4d93-acba-50ce41521ce8.png",
    "index": 163
  },
  {
    "name": "#ReverseSugarDaddy",
    "time": "4:30 PM",
    "url": "https://lu.ma/azg5nc4b",
    "location": "Fairmont Spa Austin",
    "thumbnailUrl": "90a49d93-83b1-4c38-8c0b-c476a460b53d.jpg",
    "index": 164
  },
  {
    "name": "Startup Pitch & Networking in Austin",
    "time": "6:00 PM",
    "url": "https://lu.ma/jjf2h60z",
    "location": "Austin, Texas",
    "thumbnailUrl": "447ec60d-0f6e-4853-bbbd-3aefc7d1e305.png",
    "index": 165
  }
]